pox/__init__.py
pox/__main__.py
pox/_disk.py
pox/info.py
pox/shutils.py
pox/utils.py
pox/tests/__init__.py
pox/tests/__main__.py
pox/tests/test_shutils.py
pox/tests/test_utils.py
pox-0.3.0.data/scripts/pox
pox-0.3.0.dist-info/DESCRIPTION.rst
pox-0.3.0.dist-info/METADATA
pox-0.3.0.dist-info/RECORD
pox-0.3.0.dist-info/WHEEL
pox-0.3.0.dist-info/metadata.json
pox-0.3.0.dist-info/top_level.txt
