Metadata-Version: 1.2
Name: pox
Version: 0.3.0
Summary: utilities for filesystem exploration and automated builds
Home-page: https://github.com/uqfoundation/pox
Author: Mike McKerns
Maintainer: Mike McKerns
License: 3-clause BSD
Download-URL: https://github.com/uqfoundation/pox/releases/download/pox-0.3.0/pox-0.3.0.tar.gz
Platform: Linux
Platform: Windows
Platform: Mac
Classifier: Development Status :: 5 - Production/Stable
Classifier: Intended Audience :: Developers
Classifier: Intended Audience :: Science/Research
Classifier: License :: OSI Approved :: BSD License
Classifier: Programming Language :: Python :: 2
Classifier: Programming Language :: Python :: 2.7
Classifier: Programming Language :: Python :: 3
Classifier: Programming Language :: Python :: 3.6
Classifier: Programming Language :: Python :: 3.7
Classifier: Programming Language :: Python :: 3.8
Classifier: Programming Language :: Python :: 3.9
Classifier: Topic :: Scientific/Engineering
Classifier: Topic :: Software Development
